scmer/__init__.py
scmer/_base_selector.py
scmer/_base_torch_model.py
scmer/_comparison.py
scmer/_interfaces.py
scmer/_owlqn.py
scmer/_tsne_l1.py
scmer/_tsne_torch_models.py
scmer/_umap_l1.py
scmer/_umap_torch_models.py
scmer/_utils.py
scmer-0.1.1.dist-info/LICENSE
scmer-0.1.1.dist-info/METADATA
scmer-0.1.1.dist-info/WHEEL
scmer-0.1.1.dist-info/top_level.txt
scmer-0.1.1.dist-info/RECORD
