Metadata-Version: 2.1
Name: scmer
Version: 0.1.1
Summary: Manifold preserving marker selection for single-cell data
Home-page: https://scmer.readthedocs.io/
Author: Shaoheng Liang
Author-email: 
Classifier: Programming Language :: Python :: 3
Classifier: License :: OSI Approved :: MIT License
Classifier: Operating System :: OS Independent
Requires-Python: >=3.6
License-File: LICENSE
Requires-Dist: torch
Requires-Dist: scikit-learn (==0.23.2)
Requires-Dist: numpy
Requires-Dist: scipy
Requires-Dist: pandas
Requires-Dist: seaborn
